zim_validate
