Metadata-Version: 1.1
Name: zim-validate
Version: 0.0.3
Summary: A package to validate Zimbabwean mobile numbers for Telecel,Netone,Econet or any other number from major MNOs in Zim,passports,national IDs,drivers licenses etc
Home-page: https://github.com/RONALD55/ZimPlaces-Python-Library
Author: Ronald Nyasha Kanyepi
Author-email: kanyepironald@gmail.com
License: MIT
Keywords: zimbabwe,regex in Zimbabwe,validate Zimbabwean drivers license,validate Zimbabwean passports,validate Zimbabwean mobile numbers,validate Zimbabwean national IDs,python library to validate Telecel numbers,python library to validate Netone numbers,python library to  validate Econet numbers
Platform: UNKNOWN
Classifier: Development Status :: 5 - Production/Stable
Classifier: Intended Audience :: Education
Classifier: Intended Audience :: Developers
Classifier: Operating System :: Microsoft :: Windows :: Windows 10
Classifier: License :: OSI Approved :: MIT License
Classifier: Programming Language :: Python :: 3
